gadalang_lang/__init__.py
gadalang_lang/__version__.py
gadalang_lang/_plugin.py
gadalang_lang/config.yml
gadalang_lang/test_utils.py
gadalang_lang/parser/__init__.py
gadalang_lang/parser/_json.py
gadalang_lang/parser/_yaml.py
test/__init__.py
test/utils.py
test/parser/__init__.py
test/parser/test_json.py
test/parser/test_yaml.py
gadalang_lang-0.2a0.dist-info/LICENSE
gadalang_lang-0.2a0.dist-info/METADATA
gadalang_lang-0.2a0.dist-info/WHEEL
gadalang_lang-0.2a0.dist-info/entry_points.txt
gadalang_lang-0.2a0.dist-info/top_level.txt
gadalang_lang-0.2a0.dist-info/RECORD
