Metadata-Version: 2.1
Name: gadalang-lang
Version: 0.2a0
Summary: Collection of lang nodes for gada
Home-page: https://github.com/gadalang/gadalang-lang
Author: Jeremy Morosi
Author-email: jeremymorosi@hotmail.com
License: UNKNOWN
Project-URL: Bug Tracker, https://github.com/gadalang/gadalang-lang/issues
Project-URL: Source Code, https://github.com/gadalang/gadalang-lang/
Platform: UNKNOWN
Classifier: Development Status :: 3 - Alpha
Classifier: Intended Audience :: Developers
Classifier: Topic :: Software Development :: Build Tools
Classifier: Programming Language :: Python :: 3.7
Classifier: Programming Language :: Python :: 3.8
Classifier: Programming Language :: Python :: 3.9
Requires-Python: >=3.7
